glusterhealth
